<?xml version="1.0" encoding="UTF-8"?>
<!DOCTYPE mapper PUBLIC "-//mybatis.org//DTD Mapper 3.0//EN" "http://mybatis.org/dtd/mybatis-3-mapper.dtd">
<mapper namespace="com.dstz.sys.core.dao.HolidayConfDao">
	<resultMap id="HolidayConf" type="com.dstz.sys.core.model.HolidayConf">
		<id property="id" column="id_" jdbcType="VARCHAR"/>
		<result property="name" column="name_" jdbcType="VARCHAR"/>
		<result property="system" column="system_" jdbcType="VARCHAR"/>
		<result property="year" column="year_" jdbcType="INTEGER"/>
		<result property="startDay" column="startDay_" jdbcType="DATE"/>
		<result property="endDay" column="endDay_" jdbcType="DATE"/>
		<result property="type" column="type_" jdbcType="VARCHAR"/>
		<result property="remark" column="remark_" jdbcType="VARCHAR"/>
	</resultMap>
	
	<insert id="create" parameterType="com.dstz.sys.core.model.HolidayConf">
		INSERT INTO c_holiday_conf
		(id_,name_,system_,year_,startDay_,endDay_,type_,remark_)
		VALUES 
		(#{id,jdbcType=VARCHAR}, #{name,jdbcType=VARCHAR}, #{system,jdbcType=VARCHAR}, #{year,jdbcType=INTEGER}, #{startDay,jdbcType=DATE}, #{endDay,jdbcType=DATE}, #{type,jdbcType=VARCHAR}, #{remark,jdbcType=VARCHAR})
	</insert>
	
	<select id="get"   parameterType="java.lang.String" resultMap="HolidayConf">
		SELECT * FROM c_holiday_conf 
		WHERE 
		id_=#{id}
	</select>
	
	<select id="query" parameterType="java.util.Map" resultMap="HolidayConf">
		SELECT * FROM c_holiday_conf
		<where>
			<if test="whereSql!=null">
				${whereSql}
			</if>
		</where>
		<if test="orderBySql!=null">
			ORDER BY ${orderBySql}
		</if>
		<if test="orderBySql==null">
			ORDER BY id_ DESC
		</if>
	</select>
	
	<update id="update" parameterType="com.dstz.sys.core.model.HolidayConf">
		UPDATE c_holiday_conf SET
		name_=#{name,jdbcType=VARCHAR},
		system_=#{system,jdbcType=VARCHAR},
		year_=#{year,jdbcType=INTEGER},
		startDay_=#{startDay,jdbcType=DATE},
		endDay_=#{endDay,jdbcType=DATE},
		type_=#{type,jdbcType=VARCHAR},
		remark_=#{remark,jdbcType=VARCHAR}
		WHERE
		id_=#{id}
	</update>
	
	<delete id="remove" parameterType="java.lang.String">
		DELETE FROM c_holiday_conf 
		WHERE
		id_=#{id}
	</delete>
	
	<select id="queryOne" parameterType="java.util.Map" resultMap="HolidayConf">
		select * from c_holiday_conf
		<where>
			<if test="startDay!=null">
				startDay_=#{startDay,jdbcType=DATE}
			</if>
			<if test="endDay!=null">
				and endDay_=#{endDay,jdbcType=DATE}
			</if>
			<if test="name!=null">
				and name_=#{name,jdbcType=VARCHAR}
			</if>
		</where>
	</select>
	
	
</mapper>